pyadv/__init__.py
pyadv/advnum.py
pyadv/operation.py
pyadv-0.1.dist-info/METADATA
pyadv-0.1.dist-info/RECORD
pyadv-0.1.dist-info/WHEEL
pyadv-0.1.dist-info/top_level.txt
