Metadata-Version: 2.1
Name: pyadv
Version: 0.1
Summary: Python : Advanced
Home-page: https://github.com/Preta-Crowz/PyAdv
Author: Preta
Author-email: preta@crowz.r-e.kr
License: MIT
Keywords: advpy,advanced,python,py,adv
Platform: UNKNOWN
